makka_pakka/__init__.py
makka_pakka/elfcaver.py
makka_pakka/mkpk.py
makka_pakka/mkpk_transpile.py
makka_pakka/settings.py
makka_pakka/directed_graph/directed_graph.py
makka_pakka/directed_graph/node.py
makka_pakka/elf_caver/__init__.py
makka_pakka/elf_caver/caver/code_caver.py
makka_pakka/elf_caver/caver/file_permissions.py
makka_pakka/elf_caver/exceptions/exceptions.py
makka_pakka/elf_caver/formatting/print_elf.py
makka_pakka/elf_caver/formatting/table_formatter.py
makka_pakka/elf_caver/injector/binary_injector.py
makka_pakka/elf_caver/injector/byte_extraction.py
makka_pakka/elf_caver/injector/compile.py
makka_pakka/elf_caver/injector/redirect_execution.py
makka_pakka/exceptions/exceptions.py
makka_pakka/integrating/integrate.py
makka_pakka/lib/stdlib/network.mkpk
makka_pakka/lib/stdlib/shell.mkpk
makka_pakka/lib/stdlib/syscall.mkpk
makka_pakka/linking/linker.py
makka_pakka/linking/linker_path.py
makka_pakka/linking/priority_list/__init__.py
makka_pakka/linking/priority_list/priority_list.py
makka_pakka/parsing/detect_headings.py
makka_pakka/parsing/parse.py
makka_pakka/parsing/parse_headings.py
makka_pakka/parsing/parsing_structures.py
makka_pakka/parsing/registers.py
makka_pakka/processing/___init__.py
makka_pakka/processing/data_replacement.py
makka_pakka/processing/function_replacement.py
makka_pakka/processing/process.py
makka_pakka/processing/processing_structures.py
MakkaPakka-1.0.4.dist-info/LICENSE.md
MakkaPakka-1.0.4.dist-info/METADATA
MakkaPakka-1.0.4.dist-info/WHEEL
MakkaPakka-1.0.4.dist-info/entry_points.txt
MakkaPakka-1.0.4.dist-info/top_level.txt
MakkaPakka-1.0.4.dist-info/RECORD
