Metadata-Version: 2.1
Name: MakkaPakka
Version: 1.0.4
Summary: A programming language for injecting code into ELF files.
Project-URL: Homepage, https://github.com/PandasAreBears/MakkaPakka
Project-URL: Documentation, https://lemon-bush-0f7dfc410.2.azurestaticapps.net/
Requires-Python: >=3.10
License-File: LICENSE.md
Requires-Dist: lief
Requires-Dist: pytest
Requires-Dist: pytest-cov
Requires-Dist: black
Requires-Dist: pre-commit
Requires-Dist: click
Requires-Dist: sphinx
Requires-Dist: termcolor
